abx.py
abx-0.1.0.dist-info/METADATA
abx-0.1.0.dist-info/WHEEL
abx-0.1.0.dist-info/RECORD
