Metadata-Version: 2.4
Name: abx
Version: 0.1.0
Summary: The common shared interfaces for the ABX ArchiveBox plugin ecosystem.
Requires-Python: >=3.10
Requires-Dist: django<6.0,>=5.1.1
Requires-Dist: pluggy>=1.5.0
